orangecontrib/__init__.py
orangecontrib/flowgl/__init__.py
orangecontrib/flowgl/widgets/__init__.py
orangecontrib/flowgl/widgets/flow_push.py
orangecontrib/flowgl/widgets/icons/flow_icon.svg
orange3_flowgl-0.1.0.dist-info/WHEEL
orange3_flowgl-0.1.0.dist-info/METADATA
orange3_flowgl-0.1.0.dist-info/RECORD
